bj_nlp/Preprocessing.py
bj_nlp/Testtext.py
bj_nlp/_PandaziseMixin.py
bj_nlp/_UtilsMixin.py
bj_nlp/__init__.py
bj_nlp/__main__.py
bj_nlp/blpClass.py
bj_nlp/c01_merger.py
bj_nlp/c05_wrede.py
bj_nlp/c10_wortschatz.py
bj_nlp/c11_wortschatz - Original.py
bj_nlp/diff_grammatik ###.ipynb
bj_nlp/diff_grammatik ###.py
bj_nlp/translate_tags.py
bj_nlp-0.0.4.dist-info/LICENSE
bj_nlp-0.0.4.dist-info/METADATA
bj_nlp-0.0.4.dist-info/WHEEL
bj_nlp-0.0.4.dist-info/entry_points.txt
bj_nlp-0.0.4.dist-info/top_level.txt
bj_nlp-0.0.4.dist-info/RECORD
