Metadata-Version: 2.1
Name: bj-nlp
Version: 0.0.4
Summary: Various NLP Tools
Author-email: djekra <hopsalla@gmail.com>
License: MIT
Project-URL: Homepage, https://github.com/djekra/bj_nlp
Classifier: Programming Language :: Python :: 3
Classifier: License :: OSI Approved :: MIT License
Classifier: Operating System :: OS Independent
Requires-Python: >=3.8
License-File: LICENSE
Requires-Dist: bpyth
